notebook/__init__.py
notebook/__main__.py
notebook/_version.py
notebook/app.py
notebook/custom/custom.css
notebook/static/1053.c5e410a592cf559cef17.js
notebook/static/1053.c5e410a592cf559cef17.js.map
notebook/static/1088.47e247a20947f628f48f.js
notebook/static/1088.47e247a20947f628f48f.js.map
notebook/static/1091.5c83b573cdf76e422343.js
notebook/static/1091.5c83b573cdf76e422343.js.map
notebook/static/1122.16363dcd990a9685123e.js
notebook/static/1122.16363dcd990a9685123e.js.map
notebook/static/114.3735fbb3fc442d926d2b.js
notebook/static/114.3735fbb3fc442d926d2b.js.map
notebook/static/1169.365e20294ad65df62bb4.js
notebook/static/1261.a7489136daa9b610b37f.js
notebook/static/1261.a7489136daa9b610b37f.js.map
notebook/static/131.ae628045345ebd7a085c.js
notebook/static/131.ae628045345ebd7a085c.js.map
notebook/static/1326.9297038a97bfe38e02c5.js
notebook/static/1326.9297038a97bfe38e02c5.js.map
notebook/static/1388.826f4dbe3aadaef0ba1f.js
notebook/static/1388.826f4dbe3aadaef0ba1f.js.map
notebook/static/1418.5913bb08784c217a1f0b.js
notebook/static/1418.5913bb08784c217a1f0b.js.map
notebook/static/1495.41f3debb92dfdd91c6da.js
notebook/static/1495.41f3debb92dfdd91c6da.js.map
notebook/static/1542.8f0b79431f7af2f43f1e.js
notebook/static/1542.8f0b79431f7af2f43f1e.js.map
notebook/static/1558.d1ebe7cb088451b0d7de.js
notebook/static/1558.d1ebe7cb088451b0d7de.js.map
notebook/static/1584.db28b1d69d0f7578dbf8.js
notebook/static/1584.db28b1d69d0f7578dbf8.js.map
notebook/static/1601.4154c4f9ed460feae33b.js
notebook/static/1601.4154c4f9ed460feae33b.js.map
notebook/static/1618.da67fb30732c49b969ba.js
notebook/static/1618.da67fb30732c49b969ba.js.map
notebook/static/1650.85ab5efb2717505d97cc.js
notebook/static/1650.85ab5efb2717505d97cc.js.map
notebook/static/1684.3f3d90b4128ca26af58b.js
notebook/static/1684.3f3d90b4128ca26af58b.js.map
notebook/static/1837.6bbfd9967be58e1325f1.js
notebook/static/1837.6bbfd9967be58e1325f1.js.map
notebook/static/1846.125f57ba9d5381ce2acd.js
notebook-7.3.0.dist-info/METADATA
notebook-7.3.0.dist-info/WHEEL
notebook-7.3.0.dist-info/entry_points.txt
notebook-7.3.0.dist-info/licenses/LICENSE
notebook-7.3.0.dist-info/RECORD
