Metadata-Version: 2.3
Name: notebook
Version: 7.3.0
Summary: Jupyter Notebook - A web-based notebook environment for interactive computing
Project-URL: Documentation, https://jupyter-notebook.readthedocs.io/
Project-URL: Homepage, https://github.com/jupyter/notebook
Project-URL: Source, https://github.com/jupyter/notebook
Project-URL: Tracker, https://github.com/jupyter/notebook/issues
Author-email: Jupyter Development Team <jupyter@googlegroups.com>
License: BSD 3-Clause License
Keywords: Jupyter,JupyterLab,Notebook
Classifier: Framework :: Jupyter
Classifier: Intended Audience :: Developers
Classifier: Intended Audience :: Science/Research
Classifier: Intended Audience :: System Administrators
Classifier: License :: OSI Approved :: BSD License
Classifier: Programming Language :: Python
Classifier: Programming Language :: Python :: 3.9
Classifier: Programming Language :: Python :: 3.10
Classifier: Programming Language :: Python :: 3.11
Classifier: Programming Language :: Python :: 3.12
Classifier: Programming Language :: Python :: 3.13
Classifier: Typing :: Typed
Requires-Python: >=3.8
Requires-Dist: jupyter-server<3,>=2.4.0
Requires-Dist: jupyterlab-server<3,>=2.27.1
Requires-Dist: jupyterlab<4.4,>=4.3.2
Requires-Dist: notebook-shim<0.3,>=0.2
Requires-Dist: tornado>=6.2.0
Provides-Extra: dev
Requires-Dist: hatch; extra == 'dev'
Requires-Dist: pre-commit; extra == 'dev'
Provides-Extra: docs
Requires-Dist: myst-parser; extra == 'docs'
Requires-Dist: nbsphinx; extra == 'docs'
Requires-Dist: pydata-sphinx-theme; extra == 'docs'
Requires-Dist: sphinx>=1.3.6; extra == 'docs'
Requires-Dist: sphinxcontrib-github-alt; extra == 'docs'
Requires-Dist: sphinxcontrib-spelling; extra == 'docs'
Provides-Extra: test
Requires-Dist: importlib-resources>=5.0; (python_version < '3.10') and extra == 'test'
Requires-Dist: ipykernel; extra == 'test'
Requires-Dist: jupyter-server[test]<3,>=2.4.0; extra == 'test'
Requires-Dist: jupyterlab-server[test]<3,>=2.27.1; extra == 'test'
Requires-Dist: nbval; extra == 'test'
Requires-Dist: pytest-console-scripts; extra == 'test'
Requires-Dist: pytest-timeout; extra == 'test'
Requires-Dist: pytest-tornasync; extra == 'test'
Requires-Dist: pytest>=7.0; extra == 'test'
Requires-Dist: requests; extra == 'test'
